uc_model_creator/__init__.py
uc_model_creator/main.py
uc_model_creator/uc_model_creator.py
uc_model_creator-0.0.1.dist-info/METADATA
uc_model_creator-0.0.1.dist-info/WHEEL
uc_model_creator-0.0.1.dist-info/entry_points.txt
uc_model_creator-0.0.1.dist-info/top_level.txt
uc_model_creator-0.0.1.dist-info/RECORD
