Metadata-Version: 2.1
Name: uc-model-creator
Version: 0.0.1
Summary: An tool for model creation
Home-page: UNKNOWN
License: UNKNOWN
Platform: UNKNOWN
Requires-Dist: tensorflow (==2.3.1)
Requires-Dist: opencv-python (==4.5.1.48)
